aiverify_robustness_toolbox/__init__.py
aiverify_robustness_toolbox/__main__.py
aiverify_robustness_toolbox/algo.meta.json
aiverify_robustness_toolbox/algo.py
aiverify_robustness_toolbox/algo_init.py
aiverify_robustness_toolbox/input.schema.json
aiverify_robustness_toolbox/output.schema.json
aiverify_robustness_toolbox/plugin_init.py
aiverify_robustness_toolbox-2.1.0.dist-info/METADATA
aiverify_robustness_toolbox-2.1.0.dist-info/WHEEL
aiverify_robustness_toolbox-2.1.0.dist-info/entry_points.txt
aiverify_robustness_toolbox-2.1.0.dist-info/licenses/AUTHORS.rst
aiverify_robustness_toolbox-2.1.0.dist-info/licenses/LICENSE
aiverify_robustness_toolbox-2.1.0.dist-info/licenses/NOTICE.md
aiverify_robustness_toolbox-2.1.0.dist-info/RECORD
