Metadata-Version: 2.4
Name: aiverify-robustness-toolbox
Version: 2.1.0
Summary: AI Verify Robustness Toolbox generates a perturbed dataset using boundary attack algorithm on the test dataset.
Author: AI Verify
License-File: AUTHORS.rst
License-File: LICENSE
License-File: NOTICE.md
Requires-Python: <3.13,>=3.10
Requires-Dist: aiverify-test-engine>=2.1.0
Requires-Dist: joblib==1.4.2
Requires-Dist: numpy==1.26.4
Requires-Dist: pandas==2.2.2
Requires-Dist: pillow===10.4.0
Requires-Dist: scikit-learn==1.5.2
